lazyip/__init__.py
lazyip/lazyip.py
lazyip-1.0.0.dist-info/METADATA
lazyip-1.0.0.dist-info/WHEEL
lazyip-1.0.0.dist-info/top_level.txt
lazyip-1.0.0.dist-info/RECORD
