Metadata-Version: 2.4
Name: lazyip
Version: 1.0.0
Summary: 获取ip信息，支持ipv4和ipv6
Home-page: https://gitee.com/ZeroSeeker/lazyip
Author: ZeroSeeker
Author-email: zeroseeker@foxmail.com
Classifier: Programming Language :: Python :: 3
Classifier: License :: OSI Approved :: MIT License
Classifier: Operating System :: OS Independent
Dynamic: author
Dynamic: author-email
Dynamic: classifier
Dynamic: description
Dynamic: description-content-type
Dynamic: home-page
Dynamic: summary
